main.py
geaimcpopenapi-1.0.0.dist-info/METADATA
geaimcpopenapi-1.0.0.dist-info/WHEEL
geaimcpopenapi-1.0.0.dist-info/entry_points.txt
geaimcpopenapi-1.0.0.dist-info/top_level.txt
geaimcpopenapi-1.0.0.dist-info/RECORD
