Metadata-Version: 2.4
Name: geaimcpopenapi
Version: 1.0.0
Summary: OpenAPI based MCP
Requires-Python: >=3.12
Requires-Dist: fastmcp>=2.14.0
Requires-Dist: httpx>=0.28.1
